test123test234/__init__.py
test123test234/api_client.py
test123test234/api_response.py
test123test234/configuration.py
test123test234/exceptions.py
test123test234/py.typed
test123test234/rest.py
test123test234/api/__init__.py
test123test234/api/echo_api.py
test123test234/models/__init__.py
test123test234/models/model_schema.py
test123test234/models/problem.py
test123test234/models/user.py
test123test234-1.0.5.dist-info/METADATA
test123test234-1.0.5.dist-info/WHEEL
test123test234-1.0.5.dist-info/top_level.txt
test123test234-1.0.5.dist-info/RECORD
