Metadata-Version: 2.4
Name: test123test234
Version: 1.0.5
Summary: Example.com
Home-page: https://ptyossa.pl
Author: Inno
Author-email: Inno <contact@example.com>
License-Expression: MIT
Project-URL: Repository, https://github.com/GIT_USER_ID/GIT_REPO_ID
Keywords: Example.com,api,brand,logo,colors
Requires-Python: >=3.9
Requires-Dist: urllib3<3.0.0,>=2.1.0
Requires-Dist: python-dateutil>=2.8.2
Requires-Dist: pydantic>=2
Requires-Dist: typing-extensions>=4.7.1
Dynamic: author
Dynamic: home-page
